rajnish_dc_crystal/__init__.py
rajnish_dc_crystal/cli.py
rajnish_dc_crystal/config.py
rajnish_dc_crystal/core.py
rajnish_dc_crystal/emailer.py
rajnish_dc_crystal-0.1.3.dist-info/licenses/LICENSE
rajnish_dc_crystal-0.1.3.dist-info/METADATA
rajnish_dc_crystal-0.1.3.dist-info/WHEEL
rajnish_dc_crystal-0.1.3.dist-info/entry_points.txt
rajnish_dc_crystal-0.1.3.dist-info/top_level.txt
rajnish_dc_crystal-0.1.3.dist-info/RECORD
